dam/__init__.py
dam/cli.py
dam/colors.py
dam/dam_sync.py
dam/version.py
dam_sync-0.0.3.dist-info/LICENSE.txt
dam_sync-0.0.3.dist-info/METADATA
dam_sync-0.0.3.dist-info/WHEEL
dam_sync-0.0.3.dist-info/entry_points.txt
dam_sync-0.0.3.dist-info/top_level.txt
dam_sync-0.0.3.dist-info/RECORD
